[
  {
    "name": "AGC",
    "url": "02 Japan (JAPAN)/Iwakuni MCAS (RJOI)/Iwakuni MCAS (RJOI)_AGC.png"
  },
  {
    "name": "APC RWY01",
    "url": "02 Japan (JAPAN)/Iwakuni MCAS (RJOI)/Iwakuni MCAS (RJOI)_APC_RWY01.png"
  },
  {
    "name": "APC RWY19",
    "url": "02 Japan (JAPAN)/Iwakuni MCAS (RJOI)/Iwakuni MCAS (RJOI)_APC_RWY19.png"
  },
  {
    "name": "hi tacan rwy 02",
    "url": "02 Japan (JAPAN)/Iwakuni MCAS (RJOI)/Iwakuni MCAS (RJOI) - hi_tacan_rwy_02.pdf"
  },
  {
    "name": "hi tacan y rwy 02",
    "url": "02 Japan (JAPAN)/Iwakuni MCAS (RJOI)/Iwakuni MCAS (RJOI) - hi_tacan_y_rwy_02.pdf"
  },
  {
    "name": "ils rwy 02",
    "url": "02 Japan (JAPAN)/Iwakuni MCAS (RJOI)/Iwakuni MCAS (RJOI) - ils_rwy_02.pdf"
  },
  {
    "name": "matsuyama se dep obstacle rnav",
    "url": "02 Japan (JAPAN)/Iwakuni MCAS (RJOI)/Iwakuni MCAS (RJOI) - matsuyama_se_dep_obstacle_rnav.pdf"
  },
  {
    "name": "rnav gps rwy 02",
    "url": "02 Japan (JAPAN)/Iwakuni MCAS (RJOI)/Iwakuni MCAS (RJOI) - rnav_gps_rwy_02.pdf"
  },
  {
    "name": "tacan rwy 02",
    "url": "02 Japan (JAPAN)/Iwakuni MCAS (RJOI)/Iwakuni MCAS (RJOI) - tacan_rwy_02.pdf"
  },
  {
    "name": "tacan z rwy 02",
    "url": "02 Japan (JAPAN)/Iwakuni MCAS (RJOI)/Iwakuni MCAS (RJOI) - tacan_z_rwy_02.pdf"
  }
]
