[
  {
    "name": "Airport Diagram",
    "url": "01 South Korea (ROK-US)/Sacheon AB (RKPS)/Sacheon AB (RKPS) - ADC.pdf"
  },
  {
    "name": "EOR Procedure Chart",
    "url": "01 South Korea (ROK-US)/Sacheon AB (RKPS)/Sacheon AB (RKPS)_EOR.png",
    "width": 551
  },
  {
    "name": "ILS RWY 06L (111.5)",
    "url": "01 South Korea (ROK-US)/Sacheon AB (RKPS)/Sacheon AB (RKPS) - ILS.pdf"
  },
  {
    "name": "ILS RWY 24R (108.1)",
    "url": "01 South Korea (ROK-US)/Sacheon AB (RKPS)/Sacheon AB (RKPS) - ILS.pdf",
    "page": 17
  },
  {
    "name": "TACAN RWY 06L",
    "url": "01 South Korea (ROK-US)/Sacheon AB (RKPS)/Sacheon AB (RKPS) - ILS.pdf",
    "page": 5
  },
  {
    "name": "TACAN RWY 24L",
    "url": "01 South Korea (ROK-US)/Sacheon AB (RKPS)/Sacheon AB (RKPS) - ILS.pdf",
    "page": 29
  },
  {
    "name": "Standard Arrivals",
    "url": "01 South Korea (ROK-US)/Sacheon AB (RKPS)/Sacheon AB (RKPS) - STAR.pdf"
  },
  {
    "name": "Standard Departures",
    "url": "01 South Korea (ROK-US)/Sacheon AB (RKPS)/Sacheon AB (RKPS) - SID.pdf"
  }
]